argumentative_question_classifier/Baseline.py
argumentative_question_classifier/__init__.py
argumentative_question_classifier/logistic_regression.py
argumentative_question_classifier/question_classifier.py
argumentative_question_classifier/ruberta.py
argumentative_question_classifier/ruberta_topic.py
argumentative_question_classifier/support_vector_machine.py
argumentative_question_classifier-0.97.dist-info/METADATA
argumentative_question_classifier-0.97.dist-info/WHEEL
argumentative_question_classifier-0.97.dist-info/top_level.txt
argumentative_question_classifier-0.97.dist-info/RECORD
