Metadata-Version: 2.1
Name: argumentative-question-classifier
Version: 0.97
Summary: question classifier for argumentative questions in python.
Home-page: UNKNOWN
Author: Yamen Ajjour
Author-email: yajjour@hotmail.com
License: UNKNOWN
Platform: UNKNOWN
Requires-Dist: spacy (==3.1.0)
